<?xml version="1.0" encoding="UTF-8"?><record_update table="sp_instance">
    <sp_instance action="INSERT_OR_UPDATE">
        <active>true</active>
        <class_name/>
        <color>default</color>
        <css/>
        <glyph/>
        <id/>
        <order>1</order>
        <roles/>
        <short_description/>
        <size>md</size>
        <sp_column display_value="2">7516626fc349e210302c5f2b2b0131ab</sp_column>
        <sp_widget display_value="Customer Homepage Menu">785562a7c349e210302c5f2b2b013125</sp_widget>
        <sys_class_name>sp_instance</sys_class_name>
        <sys_created_by>admin</sys_created_by>
        <sys_created_on>2025-04-27 22:57:19</sys_created_on>
        <sys_id>7b166e2bc309e210302c5f2b2b01315c</sys_id>
        <sys_mod_count>0</sys_mod_count>
        <sys_name/>
        <sys_package display_value="Plumbing Company Product Management" source="x_1662488_pcpm">42081bcec3c92210302c5f2b2b01316e</sys_package>
        <sys_policy/>
        <sys_scope display_value="Plumbing Company Product Management">42081bcec3c92210302c5f2b2b01316e</sys_scope>
        <sys_update_name>sp_instance_7b166e2bc309e210302c5f2b2b01315c</sys_update_name>
        <sys_updated_by>admin</sys_updated_by>
        <sys_updated_on>2025-04-27 22:57:19</sys_updated_on>
        <title/>
        <url/>
        <widget_parameters/>
    </sp_instance>
    <sys_translated_text action="delete_multiple" query="documentkey=7b166e2bc309e210302c5f2b2b01315c"/>
</record_update>
